<annotation>
	<folder>JPEGImages</folder>
	<filename>BikesHelmets510.png</filename>
	<path>C:\Users\Administrator\Desktop\Helmet\JPEGImages\BikesHelmets510.png</path>
	<source>
		<database>Unknown</database>
	</source>
	<size>
		<width>400</width>
		<height>267</height>
		<depth>3</depth>
	</size>
	<segmented>0</segmented>
	<object>
		<name>without helmet</name>
		<pose>Unspecified</pose>
		<truncated>0</truncated>
		<difficult>0</difficult>
		<bndbox>
			<xmin>40</xmin>
			<ymin>67</ymin>
			<xmax>70</xmax>
			<ymax>104</ymax>
		</bndbox>
	</object>
	<object>
		<name>with helmet</name>
		<pose>Unspecified</pose>
		<truncated>0</truncated>
		<difficult>0</difficult>
		<bndbox>
			<xmin>230</xmin>
			<ymin>87</ymin>
			<xmax>272</xmax>
			<ymax>125</ymax>
		</bndbox>
	</object>
	<object>
		<name>without helmet</name>
		<pose>Unspecified</pose>
		<truncated>0</truncated>
		<difficult>0</difficult>
		<bndbox>
			<xmin>293</xmin>
			<ymin>72</ymin>
			<xmax>317</xmax>
			<ymax>104</ymax>
		</bndbox>
	</object>
</annotation>
